{
  "users": [
    {
      "id": 2,
      "data": {
        "name": "Ervin Howell",
        "email": "Shanna@melissa.tv"
      }
    },
    {
      "name": "test",
      "email": "tesht@gmail.com",
      "id": 3
    },
    {
      "name": "Ahmed",
      "email": "ahmed@gmail.com",
      "id": 4
    },
    {
      "name": "zzz",
      "email": "z@gmail.com",
      "id": 5
    },
    {
      "name": "atzatzya",
      "email": "ztayzta@gmail.com",
      "id": 6
    },
    {
      "name": "testazazazazaza",
      "email": "tetstststs@gmail.com",
      "id": 7
    },
    {
      "name": "",
      "email": "",
      "id": 8
    }
  ]
}